xmu/__init__.py
xmu/containers.py
xmu/io.py
xmu/types.py
xmu/utils.py
xmu-0.1b9.dist-info/LICENSE
xmu-0.1b9.dist-info/METADATA
xmu-0.1b9.dist-info/WHEEL
xmu-0.1b9.dist-info/top_level.txt
xmu-0.1b9.dist-info/RECORD
