Metadata-Version: 2.2
Name: xmu
Version: 0.1b9
Summary: Reads and writes XML for Axiell EMu
Home-page: https://github.com/NMNH-IDSC/xmu.git
Maintainer: Adam Mansur
Maintainer-email: mansura@si.edu
License: MIT
Classifier: License :: OSI Approved :: MIT License
Classifier: Programming Language :: Python :: 3
Classifier: Programming Language :: Python :: 3 :: Only
Classifier: Programming Language :: Python :: 3.10
Classifier: Programming Language :: Python :: 3.11
Classifier: Programming Language :: Python :: 3.12
Classifier: Programming Language :: Python :: 3.13
Classifier: Topic :: Text Processing :: Markup :: XML
License-File: LICENSE
Requires-Dist: joblib
Requires-Dist: lxml
Requires-Dist: pyyaml
Dynamic: classifier
Dynamic: description
Dynamic: description-content-type
Dynamic: home-page
Dynamic: license
Dynamic: maintainer
Dynamic: maintainer-email
Dynamic: requires-dist
Dynamic: summary
